LICENSE.txt
MANIFEST.in
README.rst
setup.py
mulay/__init__.py
mulay/amqp.py
mulay/carbon.py
mulay/config.py
mulay/console.py
mulay/helpers.py
mulay/mqtt.py
mulay/slack.py
mulay.egg-info/PKG-INFO
mulay.egg-info/SOURCES.txt
mulay.egg-info/dependency_links.txt
mulay.egg-info/requires.txt
mulay.egg-info/top_level.txt
mulay.egg-info/zip-safe