Metadata-Version: 1.1
Name: mulay
Version: 0.2.0
Summary: Relay / sender library for various bus / consumer types
Home-page: https://github.com/jdcasey/mulay
Author: John Casey
Author-email: jdcasey@commonjava.org
License: GPLv3+
Keywords: graphite carbon metrics monitoring mqtt amqp slack
Platform: UNKNOWN
Classifier: Development Status :: 3 - Alpha
Classifier: Intended Audience :: Developers
Classifier: License :: OSI Approved :: GNU General Public License (GPL)
Classifier: Programming Language :: Python :: 3
Classifier: Topic :: Utilities
